guick/__init__.py
guick/_version.py
guick/gui.py
guick/py.typed
guick-0.5.dist-info/METADATA
guick-0.5.dist-info/WHEEL
guick-0.5.dist-info/top_level.txt
guick-0.5.dist-info/RECORD
