Metadata-Version: 2.2
Name: guick
Version: 0.5
Summary: Graphical User Interface for Click
Requires-Python: >=3.9
Requires-Dist: click>=8.1.0
Requires-Dist: platformdirs
Requires-Dist: tomlkit
Requires-Dist: wxpython
